{
    "_title": "「主表单」布局",
    "_page": {
        "title": "宽标签布局：column = 4, window = 0.15"
    },
    "_tabs": {
        "defaultActiveKey": "tabForm",
        "items": [
            "表单效果,tabForm",
            "对应配置,tabDesc"
        ]
    },
    "_table": {
        "columns": [
            {
                "dataIndex": "sequence",
                "title": "行号"
            },
            {
                "dataIndex": "name",
                "title": "key值"
            },
            {
                "dataIndex": "column",
                "title": "组件数量"
            },
            {
                "dataIndex": "index",
                "title": "组件索引"
            },
            {
                "dataIndex": "span",
                "title": "组件宽度"
            },
            {
                "dataIndex": "width",
                "title": "布局示例（24格布局）"
            }
        ]
    },
    "_data": [
        {
            "column": 1,
            "children": [
                "1009`1`9`4,5,15"
            ]
        },
        {
            "column": 1,
            "children": [
                "1014`1`14`4,10,10"
            ]
        },
        {
            "column": 2,
            "children": [
                "2009`1`9`4,5,5,10",
                "2105`2`5`4,5,5,10"
            ]
        },
        {
            "column": 1,
            "children": [
                "1019`1`19`4,15,5"
            ]
        },
        {
            "column": 2,
            "children": [
                "2009`1`9`4,5,10,5",
                "2110`2`10`4,5,10,5"
            ]
        },
        {
            "column": 2,
            "children": [
                "2014`1`14`4,10,5,5",
                "2105`2`5`4,10,5,5"
            ]
        },
        {
            "column": 3,
            "children": [
                "3009`1`9`4,5,5,5,5",
                "3105`2`5`4,5,5,5,5",
                "3205`3`5`4,5,5,5,5"
            ]
        },
        {
            "column": 1,
            "children": [
                "1024`1`24`4,20"
            ]
        },
        {
            "column": 2,
            "children": [
                "2009`1`9`4,5,15",
                "2115`2`15`4,5,15"
            ]
        },
        {
            "column": 2,
            "children": [
                "2014`1`14`4,10,10",
                "2110`2`10`4,10,10"
            ]
        },
        {
            "column": 2,
            "children": [
                "2019`1`19`4,15,5",
                "2105`2`5`4,15,5"
            ]
        },
        {
            "column": 3,
            "children": [
                "3010`1`10`4,5,7,7",
                "3107`2`7`4,5,7,7",
                "3207`3`7`4,5,7,7"
            ]
        },
        {
            "column": 3,
            "children": [
                "3009`1`9`4,5,5,10",
                "3105`2`5`4,5,5,10",
                "3210`3`10`4,5,5,10"
            ]
        },
        {
            "column": 3,
            "children": [
                "3009`1`9`4,5,10,5",
                "3110`2`10`4,5,10,5",
                "3205`3`5`4,5,10,5"
            ]
        },
        {
            "column": 3,
            "children": [
                "3014`1`14`4,10,5,5",
                "3105`2`5`4,10,5,5",
                "3205`3`5`4,10,5,5"
            ]
        },
        {
            "column": 2,
            "children": [
                "3010`1`10`4,6,14",
                "3114`2`14`4,6,14"
            ]
        },
        {
            "column": 2,
            "children": [
                "3018`1`18`4,14,6",
                "3106`2`6`4,14,6"
            ]
        },
        {
            "column": 4,
            "children": [
                "4009`1`9`4,5,5,5,5",
                "4105`2`5`4,5,5,5,5",
                "4205`3`5`4,5,5,5,5",
                "4305`4`5`4,5,5,5,5"
            ]
        }
    ],
    "_attribute": {
        "props": {
        },
        "hoc": {
        }
    },
    "_datatree": {
    },
    "_datalist": {
    },
    "_diagram": {
        "items": {
            "nodes": [],
            "edges": []
        }
    }
}